src/__init__.py
src/mwpdfify.py
mwpdfify-1.1.2.dist-info/LICENSE
mwpdfify-1.1.2.dist-info/METADATA
mwpdfify-1.1.2.dist-info/WHEEL
mwpdfify-1.1.2.dist-info/entry_points.txt
mwpdfify-1.1.2.dist-info/top_level.txt
mwpdfify-1.1.2.dist-info/RECORD
