Metadata-Version: 2.1
Name: mwpdfify
Version: 1.1.2
Summary: Utility for batch downloading (certain) pages from MediaWiki sites as printable PDFs.
Home-page: https://github.com/aisuneko/mwpdfify
Author: aisuneko
Author-email: iceneko@protonmail.ch
Maintainer: aisuneko
Maintainer-email: iceneko@protonmail.ch
License: LGPLv3
Keywords: wiki,MediaWiki,wikipedia,PDF,wkhtml2pdf,weasyprint,scraper
Classifier: Development Status :: 4 - Beta
Classifier: Intended Audience :: Science/Research
Classifier: License :: OSI Approved :: GNU Lesser General Public License v3 (LGPLv3)
Classifier: Operating System :: OS Independent
Classifier: Programming Language :: Python :: 3
Classifier: Topic :: Internet
License-File: LICENSE
Requires-Dist: pdfkit
Provides-Extra: pdf
Requires-Dist: weasyprint ; extra == 'pdf'
